Metadata-Version: 2.0
Name: sft-test
Version: 1.0
Summary: SynapsePay Rest Native Python Library
Home-page: https://github.com/synapsepay/SynapsePayRest-Python
Author: Synapse Financial Technologies Inc.
Author-email: help@synapsepay.com
License: MIT
Keywords: SynapsePay v3 Rest API
Platform: UNKNOWN
Classifier: Development Status :: 5 - Production/Stable
Classifier: Intended Audience :: Developers
Classifier: License :: OSI Approved :: MIT License
Classifier: Programming Language :: Python :: 3.5
Requires-Dist: requests
